{
  "common": {
    "0": {
      "name": "Bryan Le Gentil",
      "life_points": 100,
      "damages": 5,
      "weapon_id": 0
    }
  },
  "uncommon": {
    "0": {
      "name": "Bryan Le Moyen",
      "life_points": 150,
      "damages": 10,
      "weapon_id": 0
    }
  },
  "hard": {
    "0": {
      "name": "Bryan Le Barbare",
      "life_points": 200,
      "damages": 20,
      "weapon_id": 0
    }
  },
  "boss": {
    "0": {
      "name": "Bryan Le Boss Trop Fort",
      "life_points": 1000,
      "damages": 500,
      "weapon_id": 0
    }
  }
}